initializer/__init__.py
initializer/components.py
initializer/lib_handling.py
initializer/odigos_sampler.py
initializer/version.py
initializer/__pycache__/lib_handling.cpython-312.pyc
initializer/__pycache__/odigos_sampler.cpython-312.pyc
initializer/__pycache__/version.cpython-312.pyc
opamp/__init__.py
opamp/anyvalue_pb2.py
opamp/health_status.py
opamp/http_client.py
opamp/opamp_pb2.py
opamp/utils.py
opamp/__pycache__/__init__.cpython-312.pyc
opamp/__pycache__/anyvalue_pb2.cpython-312.pyc
opamp/__pycache__/health_status.cpython-312.pyc
opamp/__pycache__/http_client.cpython-312.pyc
opamp/__pycache__/opamp_pb2.cpython-312.pyc
opamp/__pycache__/utils.cpython-312.pyc
odigos_python_initializer-0.1.0.dist-info/METADATA
odigos_python_initializer-0.1.0.dist-info/WHEEL
odigos_python_initializer-0.1.0.dist-info/top_level.txt
odigos_python_initializer-0.1.0.dist-info/RECORD
